half_subtractor.v
`timescale 1ns/1ns

module half_subtractor (
	output d,
	output bo,
	input a,
	input b
);

	wire not_a;
	
	not(not_a, a);
	xor(d, a, b);
	and(bo, not_a, b);

endmodule

full_subtractor.v
`timescale 1ns/1ns

module full_subtractor(
	output diff, output bout,
	input a, input b, input bin
	);

	wire hs1_d, hs1_bo, hs2_bo;
	
	half_subtractor hs1(hs1_d, hs1_bo, a, b);
	half_subtractor hs2(diff, hs2_bo, hs1_d, bin);
	
	and(bout, hs2_bo, hs1_bo);
	
endmodule

four_bit_subtractor.v
`timescale 1ns/1ns

module four_bit_subtractor(
	output reg [4:0] d,
	input reg [3:0] a,
	input reg [3:0] b
	);

	wire b0, b1, b2, b3;
	wire d0, d1, d2, d3, d4;

	half_subtractor hs0 (d0, b0, a[0], b[0]);
	full_subtractor fs1 (d1, b1, a[1], b[1], b1);
	full_subtractor fs2 (d2, b2, a[2], b[2], b2);
	full_subtractor fs3 (d3, b3, a[3], b[3], b3);
	
	always @* d = {b3, d3, d2, d1, d0};
endmodule

four_bit_subtractor_tb.v
`timescale 1ns/1ns

module four_bit_subtractor_tb();
	reg [3:0] a;
	reg [3:0] b;
	wire [4:0] c;

	four_bit_subtractor fbs(c, a, b);		

	initial begin
		$dumpfile("test.vcd");
		$dumpvars(1, four_bit_subtractor_tb);
		a = 4'b0001;
		b = 4'b0000;
		#10
		a = 4'b0011;
		b = 4'b0001;
		#10
		a = 4'b0011;
		b = 4'b0011;
		#10
		a = 4'b0111;
		b = 4'b0011;
		#10
		a = 4'b0111;
		b = 4'b0111;
		#10
		a = 4'b1111;
		b = 4'b0111;
		#10
		a = 4'b1111;
		b = 4'b1111;
		#10
		a = 4'b1111;
		b = 4'b1111;
		#10
		a = 4'b0000;
		b = 4'b0001;
		#10
		$finish;
	end
endmodule

test.vcd
$date
	Tue Mar 08 00:09:12 2022
$end
$version
	ModelSim Version 10.5b
$end
$timescale
	1ns
$end

$scope module four_bit_subtractor_tb $end
$var reg 4 ! a [3:0] $end
$var reg 4 " b [3:0] $end
$var wire 1 # c [4] $end
$var wire 1 $ c [3] $end
$var wire 1 % c [2] $end
$var wire 1 & c [1] $end
$var wire 1 ' c [0] $end
$upscope $end
$enddefinitions $end
#0
$dumpvars
b1 !
b0 "
1'
0&
0%
0$
0#
$end
#10
b11 !
b1 "
0'
1&
#20
b11 "
0&
#30
b111 !
1%
#40
b111 "
0%
#50
b1111 !
1$
#60
b1111 "
0$
#80
b0 !
b1 "
1'
